setup.py
hog/__init__.py
hog/hog.py
hog.egg-info/PKG-INFO
hog.egg-info/SOURCES.txt
hog.egg-info/dependency_links.txt
hog.egg-info/entry_points.txt
hog.egg-info/not-zip-safe
hog.egg-info/requires.txt
hog.egg-info/top_level.txt